{
  "page": 456,
  "ayah_highlights": [
    {
      "page": 456,
      "line": 1,
      "sura": 70,
      "ayah": 1,
      "left": 0.6706409459586952,
      "right": 0.97,
      "confidence": 0.5,
      "source": "manual_marker_sync"
    },
    {
      "page": 456,
      "line": 1,
      "sura": 70,
      "ayah": 2,
      "left": 0.3402411587967492,
      "right": 0.6706409459586952,
      "confidence": 0.5,
      "source": "manual_marker_sync"
    },
    {
      "page": 456,
      "line": 1,
      "sura": 70,
      "ayah": 3,
      "left": 0.03,
      "right": 0.3402411587967492,
      "confidence": 0.5,
      "source": "manual_marker_sync"
    },
    {
      "page": 456,
      "line": 2,
      "sura": 70,
      "ayah": 4,
      "left": 0.14322882930217518,
      "right": 0.97,
      "confidence": 0.5,
      "source": "manual_marker_sync"
    },
    {
      "page": 456,
      "line": 2,
      "sura": 70,
      "ayah": 5,
      "left": 0.03,
      "right": 0.14322882930217518,
      "confidence": 0.5,
      "source": "manual_marker_sync"
    },
    {
      "page": 456,
      "line": 3,
      "sura": 70,
      "ayah": 5,
      "left": 0.790753340671827,
      "right": 0.97,
      "confidence": 0.5,
      "source": "manual_marker_sync"
    },
    {
      "page": 456,
      "line": 3,
      "sura": 70,
      "ayah": 6,
      "left": 0.5334172690287652,
      "right": 0.790753340671827,
      "confidence": 0.5,
      "source": "manual_marker_sync"
    },
    {
      "page": 456,
      "line": 3,
      "sura": 70,
      "ayah": 7,
      "left": 0.34970583660758336,
      "right": 0.5334172690287652,
      "confidence": 0.5,
      "source": "manual_marker_sync"
    },
    {
      "page": 456,
      "line": 3,
      "sura": 70,
      "ayah": 8,
      "left": 0.03,
      "right": 0.34970583660758336,
      "confidence": 0.5,
      "source": "manual_marker_sync"
    },
    {
      "page": 456,
      "line": 4,
      "sura": 70,
      "ayah": 8,
      "left": 0.9342252366063799,
      "right": 0.97,
      "confidence": 0.5,
      "source": "manual_marker_sync"
    },
    {
      "page": 456,
      "line": 4,
      "sura": 70,
      "ayah": 9,
      "left": 0.5926752455966788,
      "right": 0.9342252366063799,
      "confidence": 0.5,
      "source": "manual_marker_sync"
    },
    {
      "page": 456,
      "line": 4,
      "sura": 70,
      "ayah": 10,
      "left": 0.25712981179670186,
      "right": 0.5926752455966788,
      "confidence": 0.5,
      "source": "manual_marker_sync"
    },
    {
      "page": 456,
      "line": 4,
      "sura": 70,
      "ayah": 11,
      "left": 0.03,
      "right": 0.25712981179670186,
      "confidence": 0.5,
      "source": "manual_marker_sync"
    },
    {
      "page": 456,
      "line": 5,
      "sura": 70,
      "ayah": 11,
      "left": 0.4663958985364824,
      "right": 0.97,
      "confidence": 0.5,
      "source": "manual_marker_sync"
    },
    {
      "page": 456,
      "line": 5,
      "sura": 70,
      "ayah": 12,
      "left": 0.17537105425711486,
      "right": 0.4663958985364824,
      "confidence": 0.5,
      "source": "manual_marker_sync"
    },
    {
      "page": 456,
      "line": 5,
      "sura": 70,
      "ayah": 13,
      "left": 0.03,
      "right": 0.17537105425711486,
      "confidence": 0.5,
      "source": "manual_marker_sync"
    },
    {
      "page": 456,
      "line": 6,
      "sura": 70,
      "ayah": 13,
      "left": 0.8073734047662784,
      "right": 0.97,
      "confidence": 0.5,
      "source": "manual_marker_sync"
    },
    {
      "page": 456,
      "line": 6,
      "sura": 70,
      "ayah": 14,
      "left": 0.3551148946234497,
      "right": 0.8073734047662784,
      "confidence": 0.5,
      "source": "manual_marker_sync"
    },
    {
      "page": 456,
      "line": 6,
      "sura": 70,
      "ayah": 15,
      "left": 0.13913817395223754,
      "right": 0.3551148946234497,
      "confidence": 0.5,
      "source": "manual_marker_sync"
    },
    {
      "page": 456,
      "line": 6,
      "sura": 70,
      "ayah": 16,
      "left": 0.03,
      "right": 0.13913817395223754,
      "confidence": 0.5,
      "source": "manual_marker_sync"
    },
    {
      "page": 456,
      "line": 7,
      "sura": 70,
      "ayah": 16,
      "left": 0.8442003805765029,
      "right": 0.97,
      "confidence": 0.5,
      "source": "manual_marker_sync"
    },
    {
      "page": 456,
      "line": 7,
      "sura": 70,
      "ayah": 17,
      "left": 0.5422564578414542,
      "right": 0.8442003805765029,
      "confidence": 0.5,
      "source": "manual_marker_sync"
    },
    {
      "page": 456,
      "line": 7,
      "sura": 70,
      "ayah": 18,
      "left": 0.3311215558032331,
      "right": 0.5422564578414542,
      "confidence": 0.5,
      "source": "manual_marker_sync"
    },
    {
      "page": 456,
      "line": 7,
      "sura": 70,
      "ayah": 19,
      "left": 0.03,
      "right": 0.3311215558032331,
      "confidence": 0.5,
      "source": "manual_marker_sync"
    },
    {
      "page": 456,
      "line": 8,
      "sura": 70,
      "ayah": 19,
      "left": 0.9325568951153426,
      "right": 0.97,
      "confidence": 0.5,
      "source": "manual_marker_sync"
    },
    {
      "page": 456,
      "line": 8,
      "sura": 70,
      "ayah": 20,
      "left": 0.6303475086334485,
      "right": 0.9325568951153426,
      "confidence": 0.5,
      "source": "manual_marker_sync"
    },
    {
      "page": 456,
      "line": 8,
      "sura": 70,
      "ayah": 21,
      "left": 0.2760894636690394,
      "right": 0.6303475086334485,
      "confidence": 0.5,
      "source": "manual_marker_sync"
    },
    {
      "page": 456,
      "line": 8,
      "sura": 70,
      "ayah": 22,
      "left": 0.03,
      "right": 0.2760894636690394,
      "confidence": 0.5,
      "source": "manual_marker_sync"
    },
    {
      "page": 456,
      "line": 9,
      "sura": 70,
      "ayah": 23,
      "left": 0.569793,
      "right": 0.9700000062416233,
      "confidence": 0.5,
      "source": "manual_marker_sync"
    },
    {
      "page": 456,
      "line": 9,
      "sura": 70,
      "ayah": 24,
      "left": 0.15802483174981594,
      "right": 0.5697929937583767,
      "confidence": 0.5,
      "source": "manual_marker_sync"
    },
    {
      "page": 456,
      "line": 9,
      "sura": 70,
      "ayah": 25,
      "left": 0.03,
      "right": 0.15802483174981594,
      "confidence": 0.5,
      "source": "manual_marker_sync"
    },
    {
      "page": 456,
      "line": 10,
      "sura": 70,
      "ayah": 25,
      "left": 0.808684520081551,
      "right": 0.97,
      "confidence": 0.5,
      "source": "manual_marker_sync"
    },
    {
      "page": 456,
      "line": 10,
      "sura": 70,
      "ayah": 26,
      "left": 0.4437353964206165,
      "right": 0.808684520081551,
      "confidence": 0.5,
      "source": "manual_marker_sync"
    },
    {
      "page": 456,
      "line": 10,
      "sura": 70,
      "ayah": 27,
      "left": 0.03,
      "right": 0.4437353964206165,
      "confidence": 0.5,
      "source": "manual_marker_sync"
    },
    {
      "page": 456,
      "line": 11,
      "sura": 70,
      "ayah": 27,
      "left": 0.93370350035823,
      "right": 0.97,
      "confidence": 0.5,
      "source": "manual_marker_sync"
    },
    {
      "page": 456,
      "line": 11,
      "sura": 70,
      "ayah": 28,
      "left": 0.5666554744358869,
      "right": 0.93370350035823,
      "confidence": 0.5,
      "source": "manual_marker_sync"
    },
    {
      "page": 456,
      "line": 11,
      "sura": 70,
      "ayah": 29,
      "left": 0.16137670770635182,
      "right": 0.5666554744358869,
      "confidence": 0.5,
      "source": "manual_marker_sync"
    },
    {
      "page": 456,
      "line": 11,
      "sura": 70,
      "ayah": 30,
      "left": 0.03,
      "right": 0.16137670770635182,
      "confidence": 0.5,
      "source": "manual_marker_sync"
    },
    {
      "page": 456,
      "line": 12,
      "sura": 70,
      "ayah": 30,
      "left": 0.3624679258286985,
      "right": 0.97,
      "confidence": 0.5,
      "source": "manual_marker_sync"
    },
    {
      "page": 456,
      "line": 12,
      "sura": 70,
      "ayah": 31,
      "left": 0.03,
      "right": 0.3624679258286985,
      "confidence": 0.5,
      "source": "manual_marker_sync"
    },
    {
      "page": 456,
      "line": 13,
      "sura": 70,
      "ayah": 31,
      "left": 0.7858113294482765,
      "right": 0.97,
      "confidence": 0.5,
      "source": "manual_marker_sync"
    },
    {
      "page": 456,
      "line": 13,
      "sura": 70,
      "ayah": 32,
      "left": 0.3047585744326403,
      "right": 0.7858113294482765,
      "confidence": 0.5,
      "source": "manual_marker_sync"
    },
    {
      "page": 456,
      "line": 13,
      "sura": 70,
      "ayah": 33,
      "left": 0.03,
      "right": 0.3047585744326403,
      "confidence": 0.5,
      "source": "manual_marker_sync"
    },
    {
      "page": 456,
      "line": 14,
      "sura": 70,
      "ayah": 33,
      "left": 0.8126488942270683,
      "right": 0.97,
      "confidence": 0.5,
      "source": "manual_marker_sync"
    },
    {
      "page": 456,
      "line": 14,
      "sura": 70,
      "ayah": 34,
      "left": 0.37731041664320797,
      "right": 0.8126488942270683,
      "confidence": 0.5,
      "source": "manual_marker_sync"
    },
    {
      "page": 456,
      "line": 14,
      "sura": 70,
      "ayah": 35,
      "left": 0.03,
      "right": 0.37731041664320797,
      "confidence": 0.5,
      "source": "manual_marker_sync"
    },
    {
      "page": 456,
      "line": 15,
      "sura": 70,
      "ayah": 35,
      "left": 0.9370782327257929,
      "right": 0.97,
      "confidence": 0.5,
      "source": "manual_marker_sync"
    },
    {
      "page": 456,
      "line": 15,
      "sura": 70,
      "ayah": 36,
      "left": 0.5337556192678363,
      "right": 0.9370782327257929,
      "confidence": 0.5,
      "source": "manual_marker_sync"
    },
    {
      "page": 456,
      "line": 15,
      "sura": 70,
      "ayah": 37,
      "left": 0.1425667071543097,
      "right": 0.5337556192678363,
      "confidence": 0.5,
      "source": "manual_marker_sync"
    },
    {
      "page": 456,
      "line": 15,
      "sura": 70,
      "ayah": 38,
      "left": 0.03,
      "right": 0.1425667071543097,
      "confidence": 0.5,
      "source": "manual_marker_sync"
    },
    {
      "page": 456,
      "line": 16,
      "sura": 70,
      "ayah": 38,
      "left": 0.4515270851275111,
      "right": 0.97,
      "confidence": 0.5,
      "source": "manual_marker_sync"
    },
    {
      "page": 456,
      "line": 16,
      "sura": 70,
      "ayah": 39,
      "left": 0.03,
      "right": 0.4515270851275111,
      "confidence": 0.5,
      "source": "manual_marker_sync"
    }
  ],
  "ayah_markers": [
    {
      "page": 456,
      "sura": 70,
      "ayah": 1,
      "line": 1,
      "center_x": 0.6706409459586952,
      "center_y": 0.5964676073297843
    },
    {
      "page": 456,
      "sura": 70,
      "ayah": 2,
      "line": 1,
      "center_x": 0.3402411587967492,
      "center_y": 0.5749934647560611
    },
    {
      "page": 456,
      "sura": 70,
      "ayah": 3,
      "line": 1,
      "center_x": 0.05890396246652341,
      "center_y": 0.605636266591772
    },
    {
      "page": 456,
      "sura": 70,
      "ayah": 4,
      "line": 2,
      "center_x": 0.14322882930217518,
      "center_y": 0.6493697369215268
    },
    {
      "page": 456,
      "sura": 70,
      "ayah": 5,
      "line": 3,
      "center_x": 0.790753340671827,
      "center_y": 0.5335762696924043
    },
    {
      "page": 456,
      "sura": 70,
      "ayah": 6,
      "line": 3,
      "center_x": 0.5334172690287652,
      "center_y": 0.57554678025434
    },
    {
      "page": 456,
      "sura": 70,
      "ayah": 7,
      "line": 3,
      "center_x": 0.34970583660758336,
      "center_y": 0.49426026640867454
    },
    {
      "page": 456,
      "sura": 70,
      "ayah": 8,
      "line": 4,
      "center_x": 0.9342252366063799,
      "center_y": 0.40380872512441207
    },
    {
      "page": 456,
      "sura": 70,
      "ayah": 9,
      "line": 4,
      "center_x": 0.5926752455966788,
      "center_y": 0.45491017278202905
    },
    {
      "page": 456,
      "sura": 70,
      "ayah": 10,
      "line": 4,
      "center_x": 0.25712981179670186,
      "center_y": 0.4724751924828895
    },
    {
      "page": 456,
      "sura": 70,
      "ayah": 11,
      "line": 5,
      "center_x": 0.4663958985364824,
      "center_y": 0.47691558633349607
    },
    {
      "page": 456,
      "sura": 70,
      "ayah": 12,
      "line": 5,
      "center_x": 0.17537105425711486,
      "center_y": 0.4077195468740256
    },
    {
      "page": 456,
      "sura": 70,
      "ayah": 13,
      "line": 6,
      "center_x": 0.8073734047662784,
      "center_y": 0.4192071925570005
    },
    {
      "page": 456,
      "sura": 70,
      "ayah": 14,
      "line": 6,
      "center_x": 0.3551148946234497,
      "center_y": 0.5535131181012266
    },
    {
      "page": 456,
      "sura": 70,
      "ayah": 15,
      "line": 6,
      "center_x": 0.13913817395223754,
      "center_y": 0.5231379105667079
    },
    {
      "page": 456,
      "sura": 70,
      "ayah": 16,
      "line": 7,
      "center_x": 0.8442003805765029,
      "center_y": 0.4727194941253052
    },
    {
      "page": 456,
      "sura": 70,
      "ayah": 17,
      "line": 7,
      "center_x": 0.5422564578414542,
      "center_y": 0.5723990468869276
    },
    {
      "page": 456,
      "sura": 70,
      "ayah": 18,
      "line": 7,
      "center_x": 0.3311215558032331,
      "center_y": 0.49595246029485196
    },
    {
      "page": 456,
      "sura": 70,
      "ayah": 19,
      "line": 8,
      "center_x": 0.9325568951153426,
      "center_y": 0.4217324654425591
    },
    {
      "page": 456,
      "sura": 70,
      "ayah": 20,
      "line": 8,
      "center_x": 0.6303475086334485,
      "center_y": 0.4464485759451396
    },
    {
      "page": 456,
      "sura": 70,
      "ayah": 21,
      "line": 8,
      "center_x": 0.2760894636690394,
      "center_y": 0.4330613209903786
    },
    {
      "page": 456,
      "sura": 70,
      "ayah": 22,
      "line": 8,
      "center_x": 0.05834893337268306,
      "center_y": 0.5
    },
    {
      "page": 456,
      "sura": 70,
      "ayah": 23,
      "line": 9,
      "center_x": 0.5697929937583767,
      "center_y": 0.44034460455990154
    },
    {
      "page": 456,
      "sura": 70,
      "ayah": 24,
      "line": 9,
      "center_x": 0.15802483174981594,
      "center_y": 0.4130443761250138
    },
    {
      "page": 456,
      "sura": 70,
      "ayah": 25,
      "line": 10,
      "center_x": 0.808684520081551,
      "center_y": 0.4868553628399654
    },
    {
      "page": 456,
      "sura": 70,
      "ayah": 26,
      "line": 10,
      "center_x": 0.4437353964206165,
      "center_y": 0.4828106755417593
    },
    {
      "page": 456,
      "sura": 70,
      "ayah": 27,
      "line": 11,
      "center_x": 0.93370350035823,
      "center_y": 0.4983287890384625
    },
    {
      "page": 456,
      "sura": 70,
      "ayah": 28,
      "line": 11,
      "center_x": 0.5666554744358869,
      "center_y": 0.5086382976030696
    },
    {
      "page": 456,
      "sura": 70,
      "ayah": 29,
      "line": 11,
      "center_x": 0.16137670770635182,
      "center_y": 0.47192491628429356
    },
    {
      "page": 456,
      "sura": 70,
      "ayah": 30,
      "line": 12,
      "center_x": 0.3624679258286985,
      "center_y": 0.5
    },
    {
      "page": 456,
      "sura": 70,
      "ayah": 31,
      "line": 13,
      "center_x": 0.7858113294482765,
      "center_y": 0.48061289979603383
    },
    {
      "page": 456,
      "sura": 70,
      "ayah": 32,
      "line": 13,
      "center_x": 0.3047585744326403,
      "center_y": 0.4653075387538192
    },
    {
      "page": 456,
      "sura": 70,
      "ayah": 33,
      "line": 14,
      "center_x": 0.8126488942270683,
      "center_y": 0.514553761737856
    },
    {
      "page": 456,
      "sura": 70,
      "ayah": 34,
      "line": 14,
      "center_x": 0.37731041664320797,
      "center_y": 0.4792112254685741
    },
    {
      "page": 456,
      "sura": 70,
      "ayah": 35,
      "line": 15,
      "center_x": 0.9370782327257929,
      "center_y": 0.49073153254813967
    },
    {
      "page": 456,
      "sura": 70,
      "ayah": 36,
      "line": 15,
      "center_x": 0.5337556192678363,
      "center_y": 0.5525213330207424
    },
    {
      "page": 456,
      "sura": 70,
      "ayah": 37,
      "line": 15,
      "center_x": 0.1425667071543097,
      "center_y": 0.5679695417740239
    },
    {
      "page": 456,
      "sura": 70,
      "ayah": 38,
      "line": 16,
      "center_x": 0.4515270851275111,
      "center_y": 0.3914910820968928
    },
    {
      "page": 456,
      "sura": 70,
      "ayah": 39,
      "line": 16,
      "center_x": 0.057447318345196986,
      "center_y": 0.4538837075915433
    }
  ],
  "sura_headers": [
    {
      "page": 456,
      "sura": 70,
      "center_x": 0.5,
      "center_y": 0.0703
    }
  ]
}