{
  "page": 161,
  "ayah_highlights": [
    {
      "page": 161,
      "line": 1,
      "sura": 9,
      "ayah": 75,
      "left": 0.03,
      "right": 0.9700000000000001,
      "confidence": 0.85,
      "source": "text_proportional_renumbered"
    },
    {
      "page": 161,
      "line": 2,
      "sura": 9,
      "ayah": 75,
      "left": 0.5703009189232433,
      "right": 0.9700000000000001,
      "confidence": 0.95,
      "source": "visual_valley_renumbered"
    },
    {
      "page": 161,
      "line": 2,
      "sura": 9,
      "ayah": 76,
      "left": 0.03,
      "right": 0.5703009189232433,
      "confidence": 0.95,
      "source": "visual_valley_renumbered"
    },
    {
      "page": 161,
      "line": 3,
      "sura": 9,
      "ayah": 76,
      "left": 0.5716646571905548,
      "right": 0.9700000000000001,
      "confidence": 0.95,
      "source": "visual_valley_renumbered"
    },
    {
      "page": 161,
      "line": 3,
      "sura": 9,
      "ayah": 77,
      "left": 0.03,
      "right": 0.5716646571905548,
      "confidence": 0.95,
      "source": "visual_valley_renumbered"
    },
    {
      "page": 161,
      "line": 4,
      "sura": 9,
      "ayah": 77,
      "left": 0.23060000000000003,
      "right": 0.9700000000000001,
      "confidence": 0.95,
      "source": "visual_valley_renumbered"
    },
    {
      "page": 161,
      "line": 4,
      "sura": 9,
      "ayah": 78,
      "left": 0.03,
      "right": 0.3306,
      "confidence": 0.95,
      "source": "visual_valley_renumbered"
    },
    {
      "page": 161,
      "line": 5,
      "sura": 9,
      "ayah": 78,
      "left": 0.15810000000000002,
      "right": 0.9700000000000001,
      "confidence": 0.95,
      "source": "visual_valley_renumbered"
    },
    {
      "page": 161,
      "line": 5,
      "sura": 9,
      "ayah": 79,
      "left": 0.03,
      "right": 0.2581,
      "confidence": 0.95,
      "source": "visual_valley_renumbered"
    },
    {
      "page": 161,
      "line": 6,
      "sura": 9,
      "ayah": 79,
      "left": 0.03,
      "right": 0.9700000000000001,
      "confidence": 0.85,
      "source": "text_proportional_renumbered"
    },
    {
      "page": 161,
      "line": 7,
      "sura": 9,
      "ayah": 79,
      "left": 0.03,
      "right": 0.9700000000000001,
      "confidence": 0.85,
      "source": "text_proportional_renumbered"
    },
    {
      "page": 161,
      "line": 8,
      "sura": 9,
      "ayah": 79,
      "left": 0.22560921694606006,
      "right": 0.9700000000000001,
      "confidence": 0.95,
      "source": "visual_valley_renumbered"
    },
    {
      "page": 161,
      "line": 8,
      "sura": 9,
      "ayah": 80,
      "left": 0.03,
      "right": 0.22560921694606006,
      "confidence": 0.95,
      "source": "visual_valley_renumbered"
    },
    {
      "page": 161,
      "line": 9,
      "sura": 9,
      "ayah": 80,
      "left": 0.03,
      "right": 0.9700000000000001,
      "confidence": 0.85,
      "source": "text_proportional_renumbered"
    },
    {
      "page": 161,
      "line": 10,
      "sura": 9,
      "ayah": 80,
      "left": 0.03,
      "right": 0.9700000000000001,
      "confidence": 0.85,
      "source": "text_proportional_renumbered"
    },
    {
      "page": 161,
      "line": 11,
      "sura": 9,
      "ayah": 81,
      "left": 0.03,
      "right": 0.759949898991408,
      "confidence": 0.85,
      "source": "text_proportional_renumbered"
    },
    {
      "page": 161,
      "line": 11,
      "sura": 9,
      "ayah": 80,
      "left": 0.759949898991408,
      "right": 0.97,
      "confidence": 0.5,
      "source": "manual_marker_sync"
    },
    {
      "page": 161,
      "line": 12,
      "sura": 9,
      "ayah": 81,
      "left": 0.03,
      "right": 0.9700000000000001,
      "confidence": 0.85,
      "source": "text_proportional_renumbered"
    },
    {
      "page": 161,
      "line": 13,
      "sura": 9,
      "ayah": 81,
      "left": 0.07769213372517803,
      "right": 0.9700000000000001,
      "confidence": 0.95,
      "source": "visual_valley_renumbered"
    },
    {
      "page": 161,
      "line": 13,
      "sura": 9,
      "ayah": 82,
      "left": 0.03,
      "right": 0.07769213372517803,
      "confidence": 0.95,
      "source": "visual_valley_renumbered"
    },
    {
      "page": 161,
      "line": 14,
      "sura": 9,
      "ayah": 82,
      "left": 0.12838128094981527,
      "right": 0.9700000000000001,
      "confidence": 0.95,
      "source": "visual_valley_renumbered"
    },
    {
      "page": 161,
      "line": 14,
      "sura": 9,
      "ayah": 83,
      "left": 0.03,
      "right": 0.12838128094981527,
      "confidence": 0.95,
      "source": "visual_valley_renumbered"
    },
    {
      "page": 161,
      "line": 15,
      "sura": 9,
      "ayah": 83,
      "left": 0.03,
      "right": 0.9700000000000001,
      "confidence": 0.85,
      "source": "text_proportional_renumbered"
    },
    {
      "page": 161,
      "line": 16,
      "sura": 9,
      "ayah": 83,
      "left": 0.03,
      "right": 0.9700000000000001,
      "confidence": 0.85,
      "source": "text_proportional_renumbered"
    },
    {
      "page": 161,
      "line": 17,
      "sura": 9,
      "ayah": 83,
      "left": 0.6159480334312946,
      "right": 0.9700000000000001,
      "confidence": 0.95,
      "source": "visual_valley_renumbered"
    },
    {
      "page": 161,
      "line": 17,
      "sura": 9,
      "ayah": 84,
      "left": 0.03,
      "right": 0.6159480334312946,
      "confidence": 0.95,
      "source": "visual_valley_renumbered"
    },
    {
      "page": 161,
      "line": 18,
      "sura": 9,
      "ayah": 84,
      "left": 0.03,
      "right": 0.9700000000000001,
      "confidence": 0.85,
      "source": "text_proportional_renumbered"
    }
  ],
  "ayah_markers": [
    {
      "page": 161,
      "sura": 9,
      "ayah": 75,
      "line": 2,
      "center_x": 0.5703009189232433,
      "center_y": 0.5
    },
    {
      "page": 161,
      "sura": 9,
      "ayah": 76,
      "line": 3,
      "center_x": 0.5716646571905548,
      "center_y": 0.5
    },
    {
      "page": 161,
      "sura": 9,
      "ayah": 77,
      "line": 4,
      "center_x": 0.2753,
      "center_y": 0.5
    },
    {
      "page": 161,
      "sura": 9,
      "ayah": 78,
      "line": 5,
      "center_x": 0.1609,
      "center_y": 0.5
    },
    {
      "page": 161,
      "sura": 9,
      "ayah": 79,
      "line": 8,
      "center_x": 0.22560921694606006,
      "center_y": 0.5
    },
    {
      "page": 161,
      "sura": 9,
      "ayah": 80,
      "line": 11,
      "center_x": 0.759949898991408,
      "center_y": 0.5022825187485773
    },
    {
      "page": 161,
      "sura": 9,
      "ayah": 81,
      "line": 13,
      "center_x": 0.07769213372517803,
      "center_y": 0.5
    },
    {
      "page": 161,
      "sura": 9,
      "ayah": 82,
      "line": 14,
      "center_x": 0.12838128094981527,
      "center_y": 0.5
    },
    {
      "page": 161,
      "sura": 9,
      "ayah": 83,
      "line": 17,
      "center_x": 0.6159480334312946,
      "center_y": 0.5429356335986076
    },
    {
      "page": 161,
      "sura": 9,
      "ayah": 84,
      "line": 18,
      "center_x": 0.08,
      "center_y": 0.5
    }
  ],
  "sura_headers": []
}