{
  "page": 407,
  "imageWidth": 1269,
  "imageHeight": 2034,
  "textRegion": {
    "top": 101,
    "bottom": 1952,
    "left": 152,
    "right": 1116
  },
  "detectedLineCount": 15,
  "lineBands": [
    {
      "line": 1,
      "top": 36,
      "bottom": 167,
      "center": 102
    },
    {
      "line": 2,
      "top": 167,
      "bottom": 301,
      "center": 234
    },
    {
      "line": 3,
      "top": 301,
      "bottom": 425,
      "center": 363
    },
    {
      "line": 4,
      "top": 425,
      "bottom": 554,
      "center": 490
    },
    {
      "line": 5,
      "top": 554,
      "bottom": 686,
      "center": 620
    },
    {
      "line": 6,
      "top": 686,
      "bottom": 816,
      "center": 751
    },
    {
      "line": 7,
      "top": 816,
      "bottom": 944,
      "center": 880
    },
    {
      "line": 8,
      "top": 944,
      "bottom": 1069,
      "center": 1007
    },
    {
      "line": 9,
      "top": 1069,
      "bottom": 1201,
      "center": 1135
    },
    {
      "line": 10,
      "top": 1201,
      "bottom": 1326,
      "center": 1264
    },
    {
      "line": 11,
      "top": 1326,
      "bottom": 1457,
      "center": 1392
    },
    {
      "line": 12,
      "top": 1457,
      "bottom": 1588,
      "center": 1523
    },
    {
      "line": 13,
      "top": 1588,
      "bottom": 1713,
      "center": 1651
    },
    {
      "line": 14,
      "top": 1713,
      "bottom": 1845,
      "center": 1779
    },
    {
      "line": 15,
      "top": 1845,
      "bottom": 1992,
      "center": 1919
    }
  ],
  "nonAyahZones": [],
  "confidence": 0.85,
  "manualOverride": false,
  "method": "peak_valley_v2",
  "debug": {
    "rawBandCount": 15,
    "splitBands": 15,
    "medianHeight": 129,
    "merged": 0,
    "tallerThan1_6": 0
  }
}