{
  "page": 401,
  "imageWidth": 1269,
  "imageHeight": 2034,
  "textRegion": {
    "top": 101,
    "bottom": 1952,
    "left": 152,
    "right": 1116
  },
  "detectedLineCount": 16,
  "lineBands": [
    {
      "line": 1,
      "top": 56,
      "bottom": 163,
      "center": 110
    },
    {
      "line": 2,
      "top": 163,
      "bottom": 281,
      "center": 222
    },
    {
      "line": 3,
      "top": 281,
      "bottom": 400,
      "center": 341
    },
    {
      "line": 4,
      "top": 400,
      "bottom": 522,
      "center": 461
    },
    {
      "line": 5,
      "top": 522,
      "bottom": 641,
      "center": 582
    },
    {
      "line": 6,
      "top": 641,
      "bottom": 763,
      "center": 702
    },
    {
      "line": 7,
      "top": 763,
      "bottom": 887,
      "center": 825
    },
    {
      "line": 8,
      "top": 887,
      "bottom": 1003,
      "center": 945
    },
    {
      "line": 9,
      "top": 1003,
      "bottom": 1121,
      "center": 1062
    },
    {
      "line": 10,
      "top": 1121,
      "bottom": 1247,
      "center": 1184
    },
    {
      "line": 11,
      "top": 1247,
      "bottom": 1366,
      "center": 1307
    },
    {
      "line": 12,
      "top": 1366,
      "bottom": 1487,
      "center": 1430
    },
    {
      "line": 13,
      "top": 1487,
      "bottom": 1614,
      "center": 1551
    },
    {
      "line": 14,
      "top": 1614,
      "bottom": 1734,
      "center": 1674
    },
    {
      "line": 15,
      "top": 1734,
      "bottom": 1847,
      "center": 1791
    },
    {
      "line": 16,
      "top": 1847,
      "bottom": 1968,
      "center": 1924
    }
  ],
  "nonAyahZones": [],
  "confidence": 0.85,
  "manualOverride": false,
  "method": "peak_valley_v2",
  "debug": {
    "rawBandCount": 16,
    "splitBands": 16,
    "medianHeight": 119,
    "merged": 0,
    "tallerThan1_6": 0
  }
}