{
  "page": 393,
  "imageWidth": 1269,
  "imageHeight": 2052,
  "textRegion": {
    "top": 102,
    "bottom": 1969,
    "left": 152,
    "right": 1116
  },
  "detectedLineCount": 15,
  "lineBands": [
    {
      "line": 1,
      "top": 37,
      "bottom": 172,
      "center": 105
    },
    {
      "line": 2,
      "top": 172,
      "bottom": 286,
      "center": 229
    },
    {
      "line": 3,
      "top": 286,
      "bottom": 392,
      "center": 339
    },
    {
      "line": 4,
      "top": 392,
      "bottom": 510,
      "center": 451
    },
    {
      "line": 5,
      "top": 510,
      "bottom": 628,
      "center": 569
    },
    {
      "line": 6,
      "top": 628,
      "bottom": 760,
      "center": 694
    },
    {
      "line": 7,
      "top": 760,
      "bottom": 892,
      "center": 826
    },
    {
      "line": 8,
      "top": 1076,
      "bottom": 1184,
      "center": 1130
    },
    {
      "line": 9,
      "top": 1184,
      "bottom": 1293,
      "center": 1239
    },
    {
      "line": 10,
      "top": 1293,
      "bottom": 1415,
      "center": 1354
    },
    {
      "line": 11,
      "top": 1415,
      "bottom": 1532,
      "center": 1474
    },
    {
      "line": 12,
      "top": 1532,
      "bottom": 1638,
      "center": 1585
    },
    {
      "line": 13,
      "top": 1638,
      "bottom": 1754,
      "center": 1696
    },
    {
      "line": 14,
      "top": 1754,
      "bottom": 1863,
      "center": 1809
    },
    {
      "line": 15,
      "top": 1863,
      "bottom": 2009,
      "center": 1936
    }
  ],
  "nonAyahZones": [
    {
      "type": "sura_header",
      "top": 892,
      "bottom": 1002,
      "confidence": 0.95
    },
    {
      "type": "basmala",
      "top": 1002,
      "bottom": 1076,
      "confidence": 0.95
    }
  ],
  "confidence": 0.85,
  "manualOverride": false,
  "method": "peak_valley_v2",
  "debug": {
    "rawBandCount": 15,
    "splitBands": 15,
    "medianHeight": 114,
    "merged": 1,
    "tallerThan1_6": 1
  }
}