{
  "page": 173,
  "imageWidth": 1292,
  "imageHeight": 2070,
  "textRegion": {
    "top": 103,
    "bottom": 1987,
    "left": 155,
    "right": 1136
  },
  "detectedLineCount": 17,
  "lineBands": [
    {
      "line": 1,
      "top": 62,
      "bottom": 190,
      "center": 126
    },
    {
      "line": 2,
      "top": 190,
      "bottom": 308,
      "center": 249
    },
    {
      "line": 3,
      "top": 308,
      "bottom": 419,
      "center": 364
    },
    {
      "line": 4,
      "top": 419,
      "bottom": 531,
      "center": 475
    },
    {
      "line": 5,
      "top": 531,
      "bottom": 646,
      "center": 589
    },
    {
      "line": 6,
      "top": 646,
      "bottom": 759,
      "center": 703
    },
    {
      "line": 7,
      "top": 759,
      "bottom": 877,
      "center": 818
    },
    {
      "line": 8,
      "top": 877,
      "bottom": 987,
      "center": 932
    },
    {
      "line": 9,
      "top": 987,
      "bottom": 1106,
      "center": 1047
    },
    {
      "line": 10,
      "top": 1106,
      "bottom": 1217,
      "center": 1162
    },
    {
      "line": 11,
      "top": 1217,
      "bottom": 1337,
      "center": 1277
    },
    {
      "line": 12,
      "top": 1337,
      "bottom": 1448,
      "center": 1393
    },
    {
      "line": 13,
      "top": 1448,
      "bottom": 1554,
      "center": 1501
    },
    {
      "line": 14,
      "top": 1554,
      "bottom": 1673,
      "center": 1614
    },
    {
      "line": 15,
      "top": 1673,
      "bottom": 1785,
      "center": 1729
    },
    {
      "line": 16,
      "top": 1785,
      "bottom": 1902,
      "center": 1844
    },
    {
      "line": 17,
      "top": 1902,
      "bottom": 2027,
      "center": 1953
    }
  ],
  "nonAyahZones": [],
  "confidence": 0.85,
  "manualOverride": false,
  "method": "peak_valley_v2",
  "debug": {
    "rawBandCount": 17,
    "splitBands": 17,
    "medianHeight": 112,
    "merged": 0,
    "tallerThan1_6": 0
  }
}